try_manager/__init__.py
try_manager/try_manager.py
try_manager-0.0.1.dist-info/METADATA
try_manager-0.0.1.dist-info/WHEEL
try_manager-0.0.1.dist-info/licenses/LICENSE
try_manager-0.0.1.dist-info/RECORD
