Metadata-Version: 2.1
Name: try_manager
Version: 0.0.1
Summary: Manager for telegram bot on aiogram to use try except request without big construction in your code.
Project-URL: Homepage, https://github.com/DanyaSh/try_manager
Project-URL: Bug Tracker, https://github.com/DanyaSh/try_manager/issues
Author-email: DanyaSh <danilashundeev@gmail.com>
License-File: LICENSE
Classifier: License :: OSI Approved :: MIT License
Classifier: Operating System :: OS Independent
Classifier: Programming Language :: Python :: 3
Requires-Python: >=3.7
